{
  "attn_dim": 104,
  "attn_mode": "standard",
  "block_size": 512,
  "d_ff": 600,
  "d_model": 128,
  "decoupled_gate": true,
  "device": "mps",
  "dim_multiplier": 0,
  "dropout": 0.0,
  "embed_dim": 32,
  "geo_dim": 0,
  "head_dim": 32,
  "head_policy": "standard",
  "kv_head": null,
  "learned_temp": true,
  "mlp": "swiglu",
  "model": {
    "attn_dim": 104,
    "attn_mode": "standard",
    "block_size": 512,
    "d_ff": 600,
    "d_model": 128,
    "decoupled_gate": true,
    "device": "mps",
    "dim_multiplier": 0,
    "dropout": 0.0,
    "embed_dim": 32,
    "geo_dim": 0,
    "head_dim": 32,
    "head_policy": "standard",
    "kv_head": null,
    "learned_temp": true,
    "mlp": "swiglu",
    "n_head": 4,
    "n_layer": 12,
    "null_attn": false,
    "rope": true,
    "rope_base": 10000.0,
    "sem_dim": 104,
    "tie_qk": false,
    "vocab_size": 50257
  },
  "n_head": 4,
  "n_layer": 12,
  "null_attn": false,
  "rope": true,
  "rope_base": 10000.0,
  "sem_dim": 104,
  "tie_qk": false,
  "train": {
    "adam_betas": "0.9,0.95",
    "adam_eps": 1e-08,
    "attn_dim": 256,
    "attn_mode": "standard",
    "batch_by_seq": null,
    "batch_schedule": null,
    "batch_size": 0,
    "block": 512,
    "d_ff": 1024,
    "d_model": 256,
    "data": "fineweb_100m.npy",
    "data_dtype": "int64",
    "data_format": "auto",
    "dropout": 0.0,
    "embed_dim": 256,
    "eval_every": 0,
    "eval_iters": 20,
    "geo_dim": 0,
    "grad_accum": 0,
    "grad_clip": 0.0,
    "instrument": "rich",
    "kv_head": null,
    "layers": 12,
    "legacy_micro_steps": false,
    "lion_betas": "0.9,0.99",
    "live_plot": false,
    "log_every": 10,
    "lr": 0.0003,
    "lr_schedule": "cosine",
    "min_lr": 2.9999999999999997e-05,
    "mlp": "swiglu",
    "n_head": 2,
    "nan_lr_decay": 0.5,
    "nan_policy": "reduce_lr",
    "no_decoupled_gate": false,
    "no_learned_temp": false,
    "no_rope": false,
    "null_attn": false,
    "opt_foreach": false,
    "opt_fused": false,
    "optimizer": "adamw",
    "out_dir": "runs/mac_fw100m_l12_baseline_lr3e4_s1337",
    "resume": false,
    "resume_allow_config_mismatch": false,
    "resume_path": "None",
    "rope_base": 10000.0,
    "save_every": 0,
    "sem_dim": 0,
    "seq_schedule": null,
    "steps": 0,
    "sync_timing": false,
    "tb": false,
    "tie_qk": false,
    "tokenizer": "tiktoken",
    "val_frac": 0.1,
    "vocab_size": 50257,
    "wandb": true,
    "warmup_steps": 0,
    "weight_decay": 0.1
  },
  "vocab_size": 50257
}
